{
  "BTC-USD": "XXBTZUSD",
  "ETH-USD": "XETHZUSD",
  "XRP-USD": "XXRPZUSD",
  "SOL-USD": "SOLUSD",
  "ADA-USD": "ADAUSD",
  "DOGE-USD": "XDGUSD",
  "MATIC-USD": "MATICUSD",
  "DOT-USD": "DOTUSD",
  "AVAX-USD": "AVAXUSD",
  "LINK-USD": "LINKUSD",
  "UNI-USD": "UNIUSD",
  "ATOM-USD": "ATOMUSD",
  "LTC-USD": "XLTCZUSD",
  "BCH-USD": "BCHUSD",
  "XLM-USD": "XXLMZUSD",
  "ALGO-USD": "ALGOUSD",
  "VET-USD": "VETUSD",
  "FIL-USD": "FILUSD",
  "TRX-USD": "TRXUSD",
  "ETC-USD": "XETCZUSD",
  "AAVE-USD": "AAVEUSD",
  "GRT-USD": "GRTUSD",
  "SAND-USD": "SANDUSD",
  "MANA-USD": "MANAUSD",
  "AXS-USD": "AXSUSD"
}
